haoqiren_py/__init__.py
haoqiren_py_win32/__init__.py
haoqiren_py_win32-0.0.1.dist-info/METADATA
haoqiren_py_win32-0.0.1.dist-info/WHEEL
haoqiren_py_win32-0.0.1.dist-info/top_level.txt
haoqiren_py_win32-0.0.1.dist-info/RECORD
