Metadata-Version: 2.1
Name: haoqiren-py-win32
Version: 0.0.1
Summary: The HaoQiRen Python Win32 Functions
Home-page: http://www.haoqiren.com
Author: HaoQiRen
Author-email: haoqiren@qq.com
Maintainer: HaoQiRen
Maintainer-email: haoqiren@qq.com
License: MIT
Download-URL: http://www.haoqiren.com
Keywords: tool utils lib win32
Platform: win32
Platform: win_amd64
Requires-Python: >=3.6.8
Requires-Dist: haoqiren-py
Requires-Dist: pywin32
Requires-Dist: xlwings
